
{
    "index_levels": [
        {
            "date": "19900101",
            "index_level": 1773
        },
        {
            "date": "19910201",
            "index_level": 1892
        },
        {
            "date": "19920301",
            "index_level": 1754
        },
        {
            "date": "19930401",
            "index_level": 1493
        },
        {
            "date": "19940501",
            "index_level": 2719
        },
        {
            "date": "19950601",
            "index_level": 2641
        },
        {
            "date": "19960701",
            "index_level": 2096
        },
        {
            "date": "19970801",
            "index_level": 2830
        },
        {
            "date": "19980901",
            "index_level": 2827
        },
        {
            "date": "19991001",
            "index_level": 955
        },
        {
            "date": "20000208",
            "index_level": 1532
        },
        {
            "date": "20010202",
            "index_level": 1538
        },
        {
            "date": "20020908",
            "index_level": 1459
        },
        {
            "date": "20030908",
            "index_level": 2471
        },
        {
            "date": "20040208",
            "index_level": 1860
        }
    ]
}
